MANIFEST.in
README.md
README.rst
setup.cfg
setup.py
bin/compose_format
compose_format/__init__.py
compose_format.egg-info/PKG-INFO
compose_format.egg-info/SOURCES.txt
compose_format.egg-info/dependency_links.txt
compose_format.egg-info/not-zip-safe
compose_format.egg-info/requires.txt
compose_format.egg-info/top_level.txt
features/comments.feature
features/format.feature
features/stack.feature