Metadata-Version: 1.1
Name: compose-format
Version: 1.2.0
Summary: format docker-compose files
Home-page: http://github.com/funkwerk/compose_format
Author: Stefan Rohe
Author-email: UNKNOWN
License: MIT
Keywords: docker-compose format docker yml
Platform: UNKNOWN
Classifier: License :: OSI Approved :: MIT License
Classifier: Programming Language :: Python :: 3
Classifier: Topic :: Software Development
Classifier: Environment :: Console
Classifier: Operating System :: OS Independent
